uwmxhelper/__init__.py
uwmxhelper/adapt_ts.py
uwmxhelper/convert_MeteoSwiss.py
uwmxhelper/convert_UWOflow.py
uwmxhelper/convert_rPluvio.py
uwmxhelper/convert_rYoung.py
uwmxhelper/dryweatherflow.py
uwmxhelper/expand_df.py
uwmxhelper/greet.py
uwmxhelper/nextprime.py
uwmxhelper/plot_qq.py
uwmxhelper/plot_ts.py
uwmxhelper/plot_ts_cum.py
uwmxhelper/write_swmm_rainfall.py
uwmxhelper/write_swmm_ts.py
uwmxhelper/write_tsCSO.py
uwmxhelper-0.1.2.dist-info/METADATA
uwmxhelper-0.1.2.dist-info/WHEEL
uwmxhelper-0.1.2.dist-info/licenses/LICENSE
uwmxhelper-0.1.2.dist-info/RECORD
