Metadata-Version: 2.3
Name: uwmxhelper
Version: 0.1.2
Summary: Supports data aggregation and visualization in the field of urban water management
Author-email: "Chairs of Urban Water Management (ETH Zurich)" <sww@ifu.baug.ethz.ch>
License: Copyright (c) 2018 The Python Packaging Authority
License-File: LICENSE
Classifier: License :: OSI Approved :: MIT License
Classifier: Operating System :: OS Independent
Classifier: Programming Language :: Python :: 3
Requires-Python: >=3.7
